[
  {
    "name": "fully-verified-renders-verified",
    "verificationStarted": true,
    "sequenceComplete": true,
    "hasCheckPending": false,
    "explicitServerFailureStatus": null,
    "summaryTone": "verified",
    "hasVerificationChecks": true,
    "hardFailureDetected": false,
    "expectedOverrideSource": "summary",
    "expectedOverrideStatus": "verified",
    "expectedRenderedStatus": "verified"
  },
  {
    "name": "missing-required-check-does-not-render-verified",
    "verificationStarted": true,
    "sequenceComplete": true,
    "hasCheckPending": false,
    "explicitServerFailureStatus": null,
    "summaryTone": "warning",
    "hasVerificationChecks": true,
    "hardFailureDetected": false,
    "expectedOverrideSource": "summary",
    "expectedOverrideStatus": "warning",
    "expectedRenderedStatus": "warning"
  },
  {
    "name": "explicit-proof-failure-overrides-verified-summary",
    "verificationStarted": true,
    "sequenceComplete": true,
    "hasCheckPending": false,
    "explicitServerFailureStatus": "failed",
    "summaryTone": "verified",
    "hasVerificationChecks": true,
    "hardFailureDetected": false,
    "expectedOverrideSource": "explicit_server_failure",
    "expectedOverrideStatus": "failed",
    "expectedRenderedStatus": "failed"
  },
  {
    "name": "hard-failure-check-overrides-empty-summary",
    "verificationStarted": true,
    "sequenceComplete": true,
    "hasCheckPending": false,
    "explicitServerFailureStatus": null,
    "summaryTone": null,
    "hasVerificationChecks": true,
    "hardFailureDetected": true,
    "expectedOverrideSource": "hard_failure",
    "expectedOverrideStatus": "failed",
    "expectedRenderedStatus": "failed"
  },
  {
    "name": "hard-failure-check-overrides-verified-summary",
    "verificationStarted": true,
    "sequenceComplete": true,
    "hasCheckPending": false,
    "explicitServerFailureStatus": null,
    "summaryTone": "verified",
    "hasVerificationChecks": true,
    "hardFailureDetected": true,
    "expectedOverrideSource": "hard_failure",
    "expectedOverrideStatus": "failed",
    "expectedRenderedStatus": "failed"
  },
  {
    "name": "hard-failure-keeps-failed-summary-message",
    "verificationStarted": true,
    "sequenceComplete": true,
    "hasCheckPending": false,
    "explicitServerFailureStatus": null,
    "summaryTone": "failed",
    "hasVerificationChecks": true,
    "hardFailureDetected": true,
    "expectedOverrideSource": "summary",
    "expectedOverrideStatus": "failed",
    "expectedRenderedStatus": "failed"
  },
  {
    "name": "required-pending-suppresses-result",
    "verificationStarted": true,
    "sequenceComplete": true,
    "hasCheckPending": true,
    "explicitServerFailureStatus": null,
    "summaryTone": "warning",
    "hasVerificationChecks": true,
    "hardFailureDetected": false,
    "expectedOverrideSource": "summary",
    "expectedOverrideStatus": "warning",
    "expectedRenderedStatus": null
  },
  {
    "name": "verified-with-limitations-does-not-render-verified",
    "verificationStarted": true,
    "sequenceComplete": true,
    "hasCheckPending": false,
    "explicitServerFailureStatus": null,
    "summaryTone": "warning",
    "hasVerificationChecks": true,
    "hardFailureDetected": false,
    "expectedOverrideSource": "summary",
    "expectedOverrideStatus": "warning",
    "expectedRenderedStatus": "warning"
  },
  {
    "name": "optional-pending-suppresses-result",
    "verificationStarted": true,
    "sequenceComplete": true,
    "hasCheckPending": true,
    "explicitServerFailureStatus": null,
    "summaryTone": "verified",
    "hasVerificationChecks": true,
    "hardFailureDetected": false,
    "expectedOverrideSource": "summary",
    "expectedOverrideStatus": "verified",
    "expectedRenderedStatus": null
  },
  {
    "name": "optional-running-suppresses-result",
    "verificationStarted": true,
    "sequenceComplete": true,
    "hasCheckPending": true,
    "explicitServerFailureStatus": null,
    "summaryTone": "verified",
    "hasVerificationChecks": true,
    "hardFailureDetected": false,
    "expectedOverrideSource": "summary",
    "expectedOverrideStatus": "verified",
    "expectedRenderedStatus": null
  },
  {
    "name": "sequence-incomplete-suppresses-result",
    "verificationStarted": true,
    "sequenceComplete": false,
    "hasCheckPending": false,
    "explicitServerFailureStatus": null,
    "summaryTone": "verified",
    "hasVerificationChecks": true,
    "hardFailureDetected": false,
    "expectedOverrideSource": "summary",
    "expectedOverrideStatus": "verified",
    "expectedRenderedStatus": null
  }
]
